pi2143ooppg
