Metadata-Version: 1.0
Name: pi2143ooppg
Version: 0.2
Summary: OOP tasks with pygame
Home-page: UNKNOWN
Author: UNKNOWN
Author-email: good-i-evil@yandex.ru
License: UNKNOWN
Platform: UNKNOWN
